doki_mowstyl-1.6.0.dist-info/METADATA
doki_mowstyl-1.6.0.dist-info/WHEEL
doki_mowstyl-1.6.0.dist-info/LICENSE.md
doki.cp312-win_amd64.pyd
doki.cp312-win_amd64.lib
doki_mowstyl-1.6.0.dist-info/RECORD
