Metadata-Version: 2.1
Name: doki-Mowstyl
Version: 1.6.0
Summary: Python interface for Doki (QSimov core)
Author-Email: =?utf-8?b?SGVybsODwqFuIEluZMODwq1iaWwgZGUgbGEgQ3J1eiBDYWx2bw==?= <indikalesken@hotmail.com>
License: <h3 style="text-align: center;">GNU GENERAL PUBLIC LICENSE</h3>
Requires-Python: >=3.8
Requires-Dist: numpy>=1.19
